{
  "assignedTo": "Jennifer L. Rochon",
  "assigned_to_id": null,
  "attorney": [
    "Michael Dains Blatchley",
    "Michael C. McGregor",
    "Julie Goldsmith Reiser",
    "Benjamin Will Horowitz",
    "Jan Messerschmidt",
    "Robert David Klausner",
    "Ed Swanson",
    "Andrea Farah",
    "Kim Elaine Miller",
    "Stephen Douglas Bunch",
    "Lauren Michelle Cruz",
    "Jess Roley",
    "Carly Bittman",
    "Josh Cohen",
    "Richard C. Pepperman , II",
    "City of Birmingham Retirement and Relief System",
    "Mary McNamara",
    "Karin A. DeMasi",
    "Katherine DuBois",
    "Oliver Engebretson-Schooley",
    "Philip Biegler",
    "Molly Judith Bowen",
    "Adam F. Shearer",
    "Steven Jeffrey Toll",
    "Scott M Berman",
    "James Milligan Wilson , Jr",
    "Rebekah T. Raybuck",
    "Thomas Livezey Laughlin , IV",
    "Hannah Elizabeth Ross",
    "Nanci L. Clarence",
    "Laura Helen Posner",
    "John Christopher Browne",
    "Christian Levis",
    "Jonathan D. Uslaner",
    "Jeremy Alan Lieberman",
    "Paul A. De Genaro",
    "Daniel Kahn",
    "Adam Perry",
    "Stuart Jay Baskin",
    "Leonid Traps",
    "Charles Sullivan",
    "John Gueli",
    "Carolyn Young",
    "Christopher Michael Viapiano",
    "Jeroen Van Kwawegen",
    "Frank Strangeman"
  ],
  "attorney_id": [
    6920854,
    6920855,
    6920856,
    6920857,
    6920858,
    6920859,
    6920860,
    6920862,
    6920863,
    6920864,
    6920865,
    6920866,
    6920867,
    6920868,
    6920870,
    6920871,
    6920872,
    6920873,
    6920874,
    6920875,
    6920876,
    6920877,
    8309031,
    8309032,
    7517493,
    7517494,
    7517495,
    7517496,
    7517497,
    7517498,
    7517499,
    7517500,
    7517501,
    8080836,
    8080837,
    8080838,
    8080839,
    8080840,
    8080841,
    8662481,
    8662482,
    6488545,
    6488548,
    7711208,
    7711209,
    7288958
  ],
  "caseName": "IN RE WELLS FARGO & COMPANY SECURITIES LITIGATION",
  "case_name_full": "",
  "cause": "15:78j(b)ss Stockholder Suit",
  "chapter": null,
  "court": "District Court, S.D. New York",
  "court_citation_string": "S.D.N.Y.",
  "court_id": "nysd",
  "dateArgued": null,
  "dateFiled": "2020-06-11",
  "dateTerminated": "2023-09-08",
  "docketNumber": "1:20-cv-04494",
  "docket_absolute_url": "/docket/17244992/in-re-wells-fargo-company-securities-litigation/",
  "docket_id": 17244992,
  "firm": [
    "Sullivan & Cromwell LLP",
    "Sullivan & Cromwell LLC",
    "Clarence Dyer & Cohen LLP",
    "Bernstein Litowitz Berger and Grossmann LLP",
    "Debevoise & Plimpton LLP",
    "Sullivan & Cromwell LLP (Washington DC)",
    "Lowey Dannenberg P.C.",
    "Bernstein Litowitz Berger & Grossmann LLP",
    "Shearman & Sterling LLP (NY)",
    "Benanti and Associates",
    "Sullivan & Cromwell, LLP(NYC)",
    "Scott Scott, L.L.P. NYC)",
    "F.C.I. Berlin",
    "Cohen Milstein Sellers & Toll PLLC",
    "Pomerantz LLP",
    "Klausner Kaufman, P.A.",
    "Faruqi & Faruqi, LLP (NYC)",
    "Friedman Kaplan Seiler Adelman & Robbins LLP",
    "Cohen, Milstein, Sellers & Toll",
    "Cohen Milstein Sellers & Toll PLLC (DC)",
    "Swanson & McNamara LLP",
    "Kahn Swick & Foti, LLC",
    "Cravath Swaine and Moore"
  ],
  "firm_id": [
    801536,
    864533,
    810138,
    27679,
    35362,
    810404,
    28203,
    416812,
    531119,
    54966,
    1217,
    656837,
    157768,
    157896,
    639435,
    579148,
    861395,
    362070,
    582105,
    13915,
    653661,
    316385,
    575336,
    157805,
    227821,
    16626,
    46835,
    790390,
    43895
  ],
  "jurisdictionType": "Federal Question",
  "juryDemand": "Both",
  "meta": {
    "timestamp": "2025-04-19T09:00:23.811719Z",
    "date_created": "2020-06-12T16:02:29.865054Z",
    "score": {
      "bm25": 2874.2632
    },
    "more_docs": true
  },
  "pacer_case_id": "538541",
  "party": [
    "Louisiana Sheriffs Pension & Relief Fund",
    "DeKalb County Pension Fund",
    "Jess Roley",
    "C.  Allen Parker",
    "Adam Perry",
    "City of Birmingham Retirement and Relief System",
    "Charles W. Scharf",
    "Wells Fargo & Company",
    "Public Employees Retirement System of Mississippi",
    "Timothy J. Sloan",
    "David Coy",
    "Eagle Capital Management, LLC",
    "Elizabeth Duke",
    "Handelsbanken Fonder AB",
    "State of Rhode Island, Office of the General Treasurer, on behalf of the Employees Retirement System of Rhode Island",
    "John R. Shrewsberry"
  ],
  "party_id": [
    10557957,
    10557958,
    10557959,
    10557960,
    10557961,
    10557962,
    10557963,
    10557964,
    10557965,
    10557966,
    10557967,
    10557968,
    10557969,
    10557970,
    10557971,
    12428051
  ],
  "recap_documents": [
    {
      "absolute_url": "/docket/17244992/59/in-re-wells-fargo-company-securities-litigation/",
      "attachment_number": null,
      "cites": [],
      "description": "ORDER APPOINTING THE INSTITUTIONAL INVESTORS AS LEAD PLAINTIFF AND APPROVING THEIR SELECTION OF LEAD COUNSEL terminating 28 Motion to Appoint; terminating 28 Motion to Appoint Counsel; terminating 32 Motion to Appoint; terminating 32 Motion to Approve; terminating 36 Motion to Appoint; terminating 36 Motion to Appoint Counsel; granting 40 Motion to Appoint. Upon consideration of: (1) the Motion filed by Handelsbanken Fonder AB, Public Employees' Retirement System of Mississippi, State of Rhode Island, Office of the General Treasurer, on behalf of the Employees' Retirement System of Rhode Island, and the Louisiana Sheriffs' Pension & Relief Fund (collectively, the \"Institutional Investors\") for appointment as Lead Plaintiff and approval of their selection of Lead Counsel; (2) the Memorandum of Law in support thereof; (3) the Declaration of Hannah Ross in support thereof; and (4) all other pleadings and argument submitted to this Court; and for good cause shown, IT IS HEREBY ORDERED THAT: 1. The Institutional Investors' Motion is GRANTED. 2. The Institutional Investors are APPOINTED to serve as Lead Plaintiff pursuant to Section 21D(a)(3)(B) of the Securities Exchange Act of 1934, 15 U.S.C. § 78u-4(a)(3)(B), as amended by the Private Securities Litigation Reform Act of 1995, in the above-captioned action. 3. The Institutional Investors' selection of Lead Counsel is APPROVED, and Bernstein Litowitz Berger & Grossmann LLP and Cohen Milstein Sellers & Toll PLLC are APPOINTED as Lead Counsel for the Class. 4. All future filings in this action shall be captioned In re Wells Fargo & Company Securities Litigation. 5. The Clerk of Court is directed to conform the caption of this case to the caption used in this order. The Clerk of Court is further directed to terminate the motions pending at Dkt. Nos. 28, 32, 36, and 40. (Signed by Judge Gregory H. Woods on 8/29/2020) (mro) (Entered: 08/31/2020)",
      "docket_entry_id": 139404749,
      "document_number": 59,
      "document_type": "PACER Document",
      "entry_date_filed": "2020-08-29",
      "entry_number": 59,
      "filepath_local": "recap/gov.uscourts.nysd.538541/gov.uscourts.nysd.538541.59.0.pdf",
      "id": 144034830,
      "is_available": true,
      "meta": {
        "timestamp": "2025-04-19T09:00:23.809786Z",
        "date_created": "2020-08-31T14:02:15.663093Z"
      },
      "pacer_doc_id": "127027503412",
      "page_count": 2,
      "short_description": "Order on Motion to Appoint Counsel AND Order on Motion to Appoint Lead Plaintiff(s) AND Order on Motion to Approve AND Order on Motion to Appoint Lead Plaintiff(s) AND Order on Motion to Appoint Counsel AND Order on Motion to Appoint Lead Plaintiff(s) AND Order on Motion to Appoint Lead Plaintiff(s)",
      "snippet": "      Case 1:20-cv-04494-GHW Document 59 Filed 08/29/20 Page 1 of 2\n\n                                                        USDC SDNY\n                                                        DOCUMENT\n                   UNITED STATES DISTRICT COURT         ELECTRONICALLY FILED\n                  SOUTHERN DISTRICT OF NEW YORK         DOC #:\n                                                        DATE FILED: 8/29/2020\n                                       )\n                                       )\n"
    },
    {
      "absolute_url": "/docket/17244992/194/in-re-wells-fargo-company-securities-litigation/",
      "attachment_number": null,
      "cites": [],
      "description": "DECLARATION of Christopher M. Viapiano in Support re: 186 MOTION to Approve [Lead Plaintiffs' Motion for Final Approval of Settlement and Plan of Allocation].. Document filed by Wells Fargo & Company..(Viapiano, Christopher) (Entered: 08/24/2023)",
      "docket_entry_id": 362933078,
      "document_number": 194,
      "document_type": "PACER Document",
      "entry_date_filed": "2023-08-24",
      "entry_number": 194,
      "filepath_local": null,
      "id": 369639005,
      "is_available": false,
      "meta": {
        "timestamp": "2025-04-19T09:00:23.809786Z",
        "date_created": "2023-08-24T22:09:37.213880Z"
      },
      "pacer_doc_id": "127033944146",
      "page_count": null,
      "short_description": "Declaration in Support of Motion",
      "snippet": ""
    },
    {
      "absolute_url": "/docket/17244992/199/in-re-wells-fargo-company-securities-litigation/",
      "attachment_number": null,
      "cites": [],
      "description": "DECLARATION of Kyle S. Bingham in Support re: 186 MOTION to Approve [Lead Plaintiffs' Motion for Final Approval of Settlement and Plan of Allocation].. Document filed by Wells Fargo & Company..(Viapiano, Christopher) (Entered: 09/01/2023)",
      "docket_entry_id": 363710584,
      "document_number": 199,
      "document_type": "PACER Document",
      "entry_date_filed": "2023-09-01",
      "entry_number": 199,
      "filepath_local": null,
      "id": 370490633,
      "is_available": false,
      "meta": {
        "timestamp": "2025-04-19T09:00:23.809786Z",
        "date_created": "2023-09-01T18:08:21.595178Z"
      },
      "pacer_doc_id": "127033990621",
      "page_count": null,
      "short_description": "Declaration in Support of Motion",
      "snippet": ""
    }
  ],
  "referredTo": "Sarah Netburn",
  "referred_to_id": 9448,
  "suitNature": "850 Securities/Commodities",
  "trustee_str": null
}