[
  {
    "absolute_url": "/audio/99757/automotive-industries-pension-trust-fund-et-al-v-toshiba-corporation/",
    "caseName": "Automotive Industries Pension Trust Fund v. Toshiba Corporation",
    "case_name_full": "",
    "court": "Court of Appeals for the Ninth Circuit",
    "court_citation_string": "9th Cir.",
    "court_id": "ca9",
    "dateArgued": "2025-07-14",
    "dateReargued": null,
    "dateReargumentDenied": null,
    "docketNumber": "24-3888",
    "docket_id": 70794437,
    "download_url": "https://cdn.ca9.uscourts.gov/datastore/media/2025/07/14/24-3888.mp3",
    "duration": 2600,
    "file_size_mp3": 15673714,
    "id": 99757,
    "judge": "WARDLAW, MENDOZA, JOHNSTONE",
    "local_path": "mp3/2025/07/14/automotive_industries_pension_trust_fund_v._toshiba_corporation_cl.mp3",
    "meta": {
      "timestamp": "2025-10-07T00:55:53.542784Z",
      "date_created": "2025-07-14T21:30:31.112537Z",
      "score": {
        "bm25": 13428548000000.0
      }
    },
    "pacer_case_id": "",
    "panel_ids": [
      3371
    ],
    "sha1": "a3a2843c1aeb7090a452a38147a70233f99345c8",
    "snippet": "May it please the Court, Joseph Daley on behalf of the appellants AIPTF and Teamsters, I've asked to reserve three minutes for rebuttal. Your Honors, given the numerous moving parts in this Summary Judgment Appeal that involves one of the largest accounting frauds in history, I'd like to focus this morning on the Morrison Domestic Transaction issue and then, with the Court's indulgence, spend a few more minutes on the Japanese Law issue. Now, in Stoyes, this Court held that plaintiffs may",
    "source": "C"
  },
  {
    "absolute_url": "/audio/92577/23_2335usa-v-clay/",
    "caseName": "23_2335USA v. Clay",
    "case_name_full": "",
    "court": "Court of Appeals for the Third Circuit",
    "court_citation_string": "3rd Cir.",
    "court_id": "ca3",
    "dateArgued": "2024-06-06",
    "dateReargued": null,
    "dateReargumentDenied": null,
    "docketNumber": "",
    "docket_id": 68835514,
    "download_url": "http://www2.ca3.uscourts.gov/Oralargument/audio/23_2335USAvClay.mp3",
    "duration": 4284,
    "file_size_mp3": 25761381,
    "id": 92577,
    "judge": "",
    "local_path": "mp3/2024/06/06/23_2335usa_v._clay_cl.mp3",
    "meta": {
      "timestamp": "2024-06-28T05:04:10.292956Z",
      "date_created": "2024-06-06T21:36:04.860165Z",
      "score": {
        "bm25": 13393728000000.0
      }
    },
    "pacer_case_id": "",
    "panel_ids": [],
    "sha1": "d4495ab096e4619fdaf75624c6c2589094bf07b1",
    "snippet": "v. Al-Maliki v. Clay v. Al-Maliki v. Al-Maliki v. Al-Maliki v. Al-Maliki v. Al-Maliki v. Al-Maliki v. Al-Maliki v. Al-Maliki v. Al-Maliki v. Al-Maliki v. Al-Maliki v. Al-Maliki v. Al-Maliki Could Texas criminalize that? I think Texas criminalizing that would present interesting questions related to the sovereignty of Mexico and what Mexico could prosecute. They're not going to Ciudad Juarez to arrest anybody. They wait for my three hypothetical perpetrators to return to El Paso. They arrest them",
    "source": "C"
  },
  {
    "absolute_url": "/audio/92538/united-states-v-clay/",
    "caseName": "United States v. Clay",
    "case_name_full": "",
    "court": "Court of Appeals for the Third Circuit",
    "court_citation_string": "3rd Cir.",
    "court_id": "ca3",
    "dateArgued": "2024-06-05",
    "dateReargued": null,
    "dateReargumentDenied": null,
    "docketNumber": "23-2335",
    "docket_id": 68831717,
    "download_url": "http://www2.ca3.uscourts.gov/Oralargument/audio/23-2335USAvClay.mp3",
    "duration": 4444,
    "file_size_mp3": 26721391,
    "id": 92538,
    "judge": "",
    "local_path": "mp3/2024/06/05/united_states_v._clay_cl.mp3",
    "meta": {
      "timestamp": "2024-06-28T05:04:04.936994Z",
      "date_created": "2024-06-05T21:40:00.159334Z",
      "score": {
        "bm25": 13393642000000.0
      }
    },
    "pacer_case_id": "",
    "panel_ids": [],
    "sha1": "7192ed04e2e709c49d0905c7b32b71b62878cd2b",
    "snippet": "23-2335. Mr. Massour? Thank you, Your Honor. May it please the Court, Devin Massour on behalf of Appellant Corrigan Clay. May I please reserve two minutes for rebuttal? Granted. Thank you. Mr. Clay was convicted under a statute aimed at sex tourism and sentenced to nearly two decades in prison under a guideline designed to punish sex tourists. Yet Mr. Clay is not a sex tourist. He engaged in non-commercial incest while residing in Haiti. These facts, quite simply, Your Honor, stretch Congress's",
    "source": "C"
  },
  {
    "absolute_url": "/audio/74774/smiledirectclub-llc-v-tanja-battle/",
    "caseName": "SmileDirectClub, LLC v. Tanja Battle",
    "case_name_full": "",
    "court": "Court of Appeals for the Eleventh Circuit",
    "court_citation_string": "11th Cir.",
    "court_id": "ca11",
    "dateArgued": "2021-02-23",
    "dateReargued": null,
    "dateReargumentDenied": null,
    "docketNumber": "19-12227",
    "docket_id": 59676793,
    "download_url": "https://www.ca11.uscourts.gov/system/files_force/oral_argument_recordings/19-12227_0.mp3?download=1",
    "duration": 3783,
    "file_size_mp3": 23063786,
    "id": 74774,
    "judge": "",
    "local_path": "mp3/2021/02/23/smiledirectclub_llc_v._tanja_battle_cl.mp3",
    "meta": {
      "timestamp": "2024-06-24T03:09:28.842420Z",
      "date_created": "2021-02-23T22:31:22.438382Z",
      "score": {
        "bm25": 13290135000000.0
      }
    },
    "pacer_case_id": "",
    "panel_ids": [],
    "sha1": "13a94adc6aa8633a13d348fd4c3618ae1cdd66c9",
    "snippet": "Okay, SmileDirectClub versus Tanja Battle. General Penson, will you speak with us? Thank you, Chief Judge Pryor, and may it please the court. This court has jurisdiction to hear appeals from the class of orders denying state action immunity to state officials on legal grounds. That includes the order below, and we think that order should be reversed because the orthodontic scan rule put into effect by Georgia's governor is state action by any measure. First, on jurisdiction, if immediate appeals",
    "source": "C"
  },
  {
    "absolute_url": "/audio/74686/united-states-v-rami-ghanem/",
    "caseName": "United States v. Rami Ghanem",
    "case_name_full": "",
    "court": "Court of Appeals for the Ninth Circuit",
    "court_citation_string": "9th Cir.",
    "court_id": "ca9",
    "dateArgued": "2021-02-12",
    "dateReargued": null,
    "dateReargumentDenied": null,
    "docketNumber": "19-50278",
    "docket_id": 59251966,
    "download_url": "https://cdn.ca9.uscourts.gov/datastore/media/2021/02/12/19-50278.mp3",
    "duration": 2662,
    "file_size_mp3": 16223186,
    "id": 74686,
    "judge": "Boggs, M. Smith, Murguia",
    "local_path": "mp3/2021/02/12/united_states_v._rami_ghanem_cl.mp3",
    "meta": {
      "timestamp": "2024-06-24T03:32:31.596225Z",
      "date_created": "2021-02-13T07:30:41.208607Z",
      "score": {
        "bm25": 13289184000000.0
      }
    },
    "pacer_case_id": "",
    "panel_ids": [
      2352
    ],
    "sha1": "193482c3c14a6d0283bef291a5a77e9a81f31de5",
    "snippet": "Good morning, your honors. Ben Coleman for the appellant Rami Ghanem. My plan was to focus on the venue and jurisdictional issues, and I'll start with the venue. The flaw in the government's argument here as to venue is that they are primarily relying on the Second Circuit's decision in Catino and a few other out-of-circuit cases that rely on Catino. All those cases involve defendants who were arrested in the United States, and Catino itself makes very clear that there are two different rules.",
    "source": "C"
  },
  {
    "absolute_url": "/audio/73221/seafarers-pension-plan-v-robert-bradway/",
    "caseName": "Seafarers Pension Plan v. Robert Bradway",
    "case_name_full": "",
    "court": "Court of Appeals for the Seventh Circuit",
    "court_citation_string": "7th Cir.",
    "court_id": "ca7",
    "dateArgued": "2020-11-30",
    "dateReargued": null,
    "dateReargumentDenied": null,
    "docketNumber": "20-2244",
    "docket_id": 18697682,
    "download_url": "http://media.ca7.uscourts.gov/sound/external/ds.20-2244.20-2244_11_30_2020.mp3",
    "duration": 1876,
    "file_size_mp3": 11698221,
    "id": 73221,
    "judge": "",
    "local_path": "mp3/2020/11/30/seafarers_pension_plan_v._robert_bradway_cl.mp3",
    "meta": {
      "timestamp": "2024-06-25T06:51:50.385796Z",
      "date_created": "2020-11-30T19:30:35.917914Z",
      "score": {
        "bm25": 13282790000000.0
      }
    },
    "pacer_case_id": "",
    "panel_ids": [],
    "sha1": "55001dad5f94402506b21932115183f99d480e32",
    "snippet": "The next case for argument this morning is Seafarers Pension Plan v. Bradway. Ms. Gilden. Good morning. Please proceed, Ms. Gilden. Good morning. May it please the Court. I am Carol Gilden, and I represent the Seafarers Selection Clause in a Delaware corporation's bylaws is enforceable where its application deprives shareholders of their right to assert derivative claims under the Securities and Exchange Act of 1934. So, Ms. Gilden, before you get too far, do I take it that you concede that",
    "source": "C"
  },
  {
    "absolute_url": "/audio/72332/heirs-of-khalid-abu-al-qarqani-v-chevron-corporation/",
    "caseName": "Heirs of Khalid Abu Al-Qarqani v. Chevron Corporation",
    "case_name_full": "",
    "court": "Court of Appeals for the Ninth Circuit",
    "court_citation_string": "9th Cir.",
    "court_id": "ca9",
    "dateArgued": "2020-10-19",
    "dateReargued": null,
    "dateReargumentDenied": null,
    "docketNumber": "19-17074",
    "docket_id": 18552139,
    "download_url": "https://cdn.ca9.uscourts.gov/datastore/media/2020/10/19/19-17074.mp3",
    "duration": 1624,
    "file_size_mp3": 9995175,
    "id": 72332,
    "judge": "Kelly, Thomas, Miller",
    "local_path": "mp3/2020/10/19/heirs_of_khalid_abu_al-qarqani_v._chevron_corporation_cl.mp3",
    "meta": {
      "timestamp": "2024-06-25T06:54:01.035009Z",
      "date_created": "2020-10-19T23:30:45.101648Z",
      "score": {
        "bm25": 13279161000000.0
      }
    },
    "pacer_case_id": "",
    "panel_ids": [
      3205,
      8603
    ],
    "sha1": "2034a08440dec328de9b53620f2055d62e65bbf8",
    "snippet": "Good morning your honors and may it please the court I would like to reserve five minutes for rebuttal. Appellants are landowners of property located in Ras Nura Saudi Arabia where one of the largest oil refineries in the world is located today. This land is specifically identified in Article 2 of a 1933 oil concession agreement that was entered into between the Kingdom of Saudi Arabia and SoCal, present-day Chevron. In 1949 the Kingdom of Saudi Arabia by royal decree of the King of Saudi Arabia",
    "source": "C"
  },
  {
    "absolute_url": "/audio/68451/linda-boal-v-depuy-orthopedics-inc/",
    "caseName": "Linda Boal v. DePuy Orthopedics Inc",
    "case_name_full": "",
    "court": "Court of Appeals for the Sixth Circuit",
    "court_citation_string": "6th Cir.",
    "court_id": "ca6",
    "dateArgued": "2020-02-05",
    "dateReargued": null,
    "dateReargumentDenied": null,
    "docketNumber": "19-3494",
    "docket_id": 16806694,
    "download_url": "http://www.opn.ca6.uscourts.gov/internet/court_audio/recent/02-05-2020 - Wednesday/19-3494 Linda Boal v DePuy Orthopedics Inc et al.mp3",
    "duration": 2001,
    "file_size_mp3": 12405053,
    "id": 68451,
    "judge": "",
    "local_path": "mp3/2020/02/05/linda_boal_v._depuy_orthopedics_inc_cl_1.mp3",
    "meta": {
      "timestamp": "2024-06-25T07:29:26.727203Z",
      "date_created": "2020-02-05T16:48:43.400957Z",
      "score": {
        "bm25": 13256957000000.0
      }
    },
    "pacer_case_id": "",
    "panel_ids": [],
    "sha1": "af75cd35da7a49a22af33b8b7853bf816db7a30c",
    "snippet": "Lead case number 19-3494, Linda Boal et al. v. DePuy Orthopedics Inc. et al. with 11 consolidated cases. Oral argument not to exceed 15 minutes per side. Mr. Sprague for the appellate. Mr. Sprague for the appellate. May it please the court, Aaron Sprague for the appellants. I'm going to reserve 5 minutes for rebuttal. I think it's appropriate to start with what is now the elephant in the room, which is subject matter jurisdiction. I thought it was kind of fun in your pleadings that you filed",
    "source": "C"
  },
  {
    "absolute_url": "/audio/38676/sec-v-traffic-monsoon-peggy-hunt-amicus-curiae/",
    "caseName": "SEC v. Traffic Monsoon, Peggy Hunt, Amicus Curiae",
    "case_name_full": "",
    "court": "Court of Appeals for the Tenth Circuit",
    "court_citation_string": "10th Cir.",
    "court_id": "ca10",
    "dateArgued": "2018-05-15",
    "dateReargued": null,
    "dateReargumentDenied": null,
    "docketNumber": "17-4059",
    "docket_id": 7823224,
    "download_url": "https://www.ca10.uscourts.gov/sites/default/files/clerk/17-4059.mp3",
    "duration": 2305,
    "file_size_mp3": 14112115,
    "id": 38676,
    "judge": "",
    "local_path": "mp3/2018/05/15/sec_v._traffic_monsoon_peggy_hunt_amicus_curiae_cl.mp3",
    "meta": {
      "timestamp": "2024-06-25T09:17:19.324864Z",
      "date_created": "2018-09-07T18:05:25.098707Z",
      "score": {
        "bm25": 13202438000000.0
      }
    },
    "pacer_case_id": "",
    "panel_ids": [],
    "sha1": "e9dd85e492a8c8429dd0a1643e934fa264629122",
    "snippet": "Your argument is SEC v. Traffic Monsoon. Thank you, Your Honor. May it please the Court and Counsel, my name is Lauren Washburn, and I represent Charles Scoville, and pursuant to a recent order from the District Court, represent for these purposes Traffic Monsoon as well. What was that recent order? Because that was an issue, whether Traffic Monsoon was properly before us. Yes, Your Honor. And the recent order, we filed a motion just within the last couple of days, but it's my understanding is",
    "source": "C"
  },
  {
    "absolute_url": "/audio/36020/cabello-rondon-v-dow-jones/",
    "caseName": "Cabello-Rondon v. Dow Jones &",
    "case_name_full": "",
    "court": "Court of Appeals for the Second Circuit",
    "court_citation_string": "2d Cir.",
    "court_id": "ca2",
    "dateArgued": "2018-04-13",
    "dateReargued": null,
    "dateReargumentDenied": null,
    "docketNumber": "17-2895",
    "docket_id": 6363021,
    "download_url": "http://www.ca2.uscourts.gov/decisions/isysquery/7fd8fcd4-149c-42b1-827d-76a173ebb577/1/doc/17-2895.mp3",
    "duration": 1256,
    "file_size_mp3": 7887404,
    "id": 36020,
    "judge": "",
    "local_path": "mp3/2018/04/13/cabello-rondon_v._dow_jones__cl.mp3",
    "meta": {
      "timestamp": "2024-06-25T09:23:07.779647Z",
      "date_created": "2018-04-13T19:31:32.866333Z",
      "score": {
        "bm25": 13199674000000.0
      }
    },
    "pacer_case_id": "",
    "panel_ids": [],
    "sha1": "fe5a0921f56353254d12cfdfc267c4457e9a56fd",
    "snippet": "The first case on the calendar is Cabello-Rondon v. Dow Jones Company. Thank you. You can take the podium. Good morning. Good morning, your honor. Good morning, your honors. And this is Xin Jian Zhao, here for the appellant, Dio Stato Cabello. And I've already reserved time for rebuttal. The district court aired here for two reasons. Despite acknowledging in its order on page 38 of the appellant's appendix that read liberally, Mr. Cabello has pled, and I'll quote from the order, that, quote, Dow",
    "source": "C"
  }
]