[
  {
    "resource_uri": "https://www.courtlistener.com/api/rest/v4/clusters/10338137/",
    "id": 10338137,
    "absolute_url": "/opinion/10338137/united-states-v-elizabeth-holmes/",
    "panel": [],
    "non_participating_judges": [],
    "docket_id": 66746322,
    "docket": "https://www.courtlistener.com/api/rest/v4/dockets/66746322/",
    "sub_opinions": [
      "https://www.courtlistener.com/api/rest/v4/opinions/10804725/"
    ],
    "citations": [
      {
        "date_created": "2025-11-17T13:38:05.291049-08:00",
        "date_modified": "2025-11-17T13:38:05.291058-08:00",
        "volume": "129",
        "reporter": "F.4th",
        "page": "636",
        "type": 1
      }
    ],
    "cluster_redirections": [],
    "date_created": "2025-02-24T09:01:22.340566-08:00",
    "date_modified": "2025-02-24T09:02:09.153676-08:00",
    "judges": "",
    "date_filed": "2025-02-24",
    "date_filed_is_approximate": false,
    "slug": "united-states-v-elizabeth-holmes",
    "case_name_short": "",
    "case_name": "United States v. Elizabeth Holmes",
    "case_name_full": "",
    "scdb_id": "",
    "scdb_decision_direction": null,
    "scdb_votes_majority": null,
    "scdb_votes_minority": null,
    "source": "C",
    "procedural_history": "",
    "attorneys": "",
    "nature_of_suit": "",
    "posture": "",
    "syllabus": "",
    "headnotes": "",
    "summary": "",
    "disposition": "",
    "history": "",
    "other_dates": "",
    "cross_reference": "",
    "correction": "",
    "citation_count": 5,
    "precedential_status": "Published",
    "date_blocked": null,
    "blocked": false,
    "filepath_json_harvard": null,
    "filepath_pdf_harvard": null,
    "filepath_xml_scan": null,
    "filepath_pdf_scan": null,
    "arguments": "",
    "headmatter": ""
  }
]