{
  "assignedTo": "David C. Godbey",
  "assigned_to_id": 1220,
  "attorney": [
    "Adam M Apton",
    "Francis P McConville",
    "Lawrence Levit",
    "James E Cecchi",
    "Jeremy Alan Lieberman",
    "Thomas Henry Przybylowski",
    "Richard B Harper",
    "James J Beha , II",
    "Jessica B Pulliam",
    "Kirstie L. Wallace",
    "Justin David D'Aloia",
    "Robert A. Hoffman",
    "Amy Pharr Hefley",
    "Willie C Briscoe",
    "John Benjamin Lawrence",
    "Laurence M Rosen"
  ],
  "attorney_id": [
    9497408,
    9497409,
    9497410,
    9497411,
    9497412,
    9497413,
    9497414,
    9863612,
    10570066,
    9863611,
    9497401,
    9497402,
    9497403,
    9497404,
    9497406,
    9497407
  ],
  "caseName": "IN RE AT&T SECURITIES LITIGATION",
  "case_name_full": "",
  "cause": "15:78m(a) Securities Exchange Act",
  "chapter": null,
  "court": "District Court, N.D. Texas",
  "court_citation_string": "N.D. Tex.",
  "court_id": "txnd",
  "dateArgued": null,
  "dateFiled": "2024-05-20",
  "dateTerminated": null,
  "docketNumber": "3:24-cv-01196",
  "docket_absolute_url": "/docket/68548793/in-re-att-securities-litigation/",
  "docket_id": 68548793,
  "firm": [
    "Carella Byrne Cecchi Brody & Agnello PC",
    "Pomerantz LLP",
    "Pomerantz, LLP",
    "Baker Botts L.L.P.",
    "Levi & Korsinsky LLP",
    "Abraham, Fruchter & Twersky, LLP",
    "Labaton Keller Sucharow LLP",
    "Baker Botts LLP",
    "Amy Pharr Hefley",
    "Pomenrantz LLCp",
    "Carella, Byrne, Cecchi, Olstein, Brody & Agnello, PC",
    "The Briscoe Law Firm, PLLC"
  ],
  "firm_id": [
    343904,
    954784,
    1074592,
    33539,
    17475,
    871048,
    36555,
    337709,
    934350,
    993951,
    903188,
    449687,
    19928,
    27679
  ],
  "jurisdictionType": "Federal Question",
  "juryDemand": "Plaintiff",
  "meta": {
    "timestamp": "2025-07-31T14:24:18.265067Z",
    "date_created": "2024-05-21T02:46:15.149836Z",
    "score": {
      "bm25": 1316.7006
    },
    "more_docs": false
  },
  "pacer_case_id": "390009",
  "party": [
    "AT&T Inc Securities Litigation",
    "John Brazinsky",
    "Suresh Kodali",
    "John Stephens",
    "New York City Police Pension Fund",
    "Jeffrey S. McElfresh",
    "John T Stankey",
    "Velliv, Pension& Livsforsikring A/S",
    "Bridget N Smagala Revocable Trust",
    "Pascal Desroches",
    "Teachers Retirement System of the City of New York",
    "Randall L Stephenson",
    "Haresh Joshi",
    "Board of Education Retirement System of the City of New York",
    "AT&T Inc",
    "New York City Fire Department Pension Fund",
    "New York City Employees' Retirement System",
    "General Retirement System of the City of Detroit",
    "New Mexico State Investment Council"
  ],
  "party_id": [
    14103632,
    14103633,
    14103634,
    14103635,
    14103636,
    14103637,
    14103638,
    14654672,
    14103640,
    14103642,
    14103643,
    14103644,
    14103645,
    14103646,
    14103647,
    14103648,
    14103649,
    14103650,
    14103651
  ],
  "recap_documents": [
    {
      "absolute_url": "/docket/68548793/70/in-re-att-securities-litigation/",
      "attachment_number": null,
      "cites": [
        31529,
        32188,
        37736,
        62908,
        142888,
        2410677,
        2451994,
        2477962,
        2828911,
        3169454,
        4162446,
        4318025,
        4365805,
        4426802,
        7233605,
        7236671,
        7240002,
        7242291,
        7242966,
        7247821,
        7249472,
        7250630,
        7252106,
        8413181,
        8413488,
        9414160,
        9435031,
        11066691
      ],
      "description": "MOTION to Dismiss First Amended Class Action Complaint filed by AT&T Inc, Pascal Desroches, Jeffrey S. McElfresh, John T Stankey, John Stephens, Randall L Stephenson with Brief/Memorandum in Support. (Attachments: # 1 Exhibit(s) Appendix in Support of Motion to Dismiss First Amended Class Action Complaint, # 2 Proposed Order)Attorney Jessica B Pulliam added to party Jeffrey S. McElfresh(pty:dft) (Pulliam, Jessica) (Entered: 09/06/2024)",
      "docket_entry_id": 404222649,
      "document_number": 70,
      "document_type": "PACER Document",
      "entry_date_filed": "2024-09-06",
      "entry_number": 70,
      "filepath_local": "recap/gov.uscourts.txnd.390009/gov.uscourts.txnd.390009.70.0.pdf",
      "id": 414694000,
      "is_available": true,
      "meta": {
        "timestamp": "2025-07-31T14:24:18.245022Z",
        "date_created": "2024-10-04T06:13:56.161104Z"
      },
      "pacer_doc_id": "177017111607",
      "page_count": 40,
      "short_description": "",
      "snippet": "Case 3:24-cv-01196-N   Document 70   Filed 09/06/24   Page 1 of 40   PageID 245\n\n\n\n                  IN THE UNITED STATES DISTRICT COURT\n                  FOR THE NORTHERN DISTRICT OF TEXAS\n                            DALLAS DIVISION\n\n\n\n\nIN RE AT&T INC. SECURITIES                Case No. 3:24-cv-01196-N\nLITIGATION\n\n\n\n\n     MOTION TO DISMISS FIRST AMENDED CLASS ACTION COMPLAINT\n                       AND BRIEF IN SUPPORT\n\fCase 3:24-cv-01196-N                       Document 70                 File"
    }
  ],
  "referredTo": null,
  "referred_to_id": null,
  "suitNature": "850 Other Statutes: Securities/Commodities/Exchange",
  "trustee_str": null
}